setup.py
warden/__init__.py
warden.egg-info/PKG-INFO
warden.egg-info/SOURCES.txt
warden.egg-info/dependency_links.txt
warden.egg-info/top_level.txt