Metadata-Version: 1.1
Name: warden
Version: 0.0.1a
Summary: A set of tools for monitoring Python applications, and shipping events to Sentry and metrics to Graphite
Home-page: https://github.com/matthewhampton/warden
Author: Matthew Hampton
Author-email: support@sjsoft.com
License: Python Software Foundation License
Keywords: sentry carbon graphite monitoring
Platform: UNKNOWN
Classifier: Development Status :: 2 - Pre-Alpha
Classifier: Intended Audience :: Developers
Classifier: Programming Language :: Python
Classifier: License :: OSI Approved :: Python Software Foundation License
Classifier: Environment :: Web Environment
Classifier: Operating System :: Microsoft :: Windows
Classifier: Operating System :: POSIX
Classifier: Programming Language :: Python
Classifier: Topic :: System :: Monitoring
Classifier: Topic :: Software Development :: Libraries
Classifier: Topic :: Software Development :: Libraries :: Python Modules
